README.md
setup.py
pulumi_gcp_native/__init__.py
pulumi_gcp_native/_tables.py
pulumi_gcp_native/_utilities.py
pulumi_gcp_native/provider.py
pulumi_gcp_native/py.typed
pulumi_gcp_native.egg-info/PKG-INFO
pulumi_gcp_native.egg-info/SOURCES.txt
pulumi_gcp_native.egg-info/dependency_links.txt
pulumi_gcp_native.egg-info/not-zip-safe
pulumi_gcp_native.egg-info/requires.txt
pulumi_gcp_native.egg-info/top_level.txt
pulumi_gcp_native/accesscontextmanager/__init__.py
pulumi_gcp_native/accesscontextmanager/v1/__init__.py
pulumi_gcp_native/accesscontextmanager/v1/_inputs.py
pulumi_gcp_native/accesscontextmanager/v1/access_policy.py
pulumi_gcp_native/accesscontextmanager/v1/access_policy_access_level.py
pulumi_gcp_native/accesscontextmanager/v1/access_policy_service_perimeter.py
pulumi_gcp_native/accesscontextmanager/v1/organization_gcp_user_access_binding.py
pulumi_gcp_native/accesscontextmanager/v1/outputs.py
pulumi_gcp_native/accesscontextmanager/v1beta/__init__.py
pulumi_gcp_native/accesscontextmanager/v1beta/_inputs.py
pulumi_gcp_native/accesscontextmanager/v1beta/access_policy.py
pulumi_gcp_native/accesscontextmanager/v1beta/access_policy_access_level.py
pulumi_gcp_native/accesscontextmanager/v1beta/access_policy_service_perimeter.py
pulumi_gcp_native/accesscontextmanager/v1beta/outputs.py
pulumi_gcp_native/apigateway/__init__.py
pulumi_gcp_native/apigateway/v1/__init__.py
pulumi_gcp_native/apigateway/v1/_inputs.py
pulumi_gcp_native/apigateway/v1/api.py
pulumi_gcp_native/apigateway/v1/api_config.py
pulumi_gcp_native/apigateway/v1/api_config_iam_policy.py
pulumi_gcp_native/apigateway/v1/api_iam_policy.py
pulumi_gcp_native/apigateway/v1/gateway.py
pulumi_gcp_native/apigateway/v1/gateway_iam_policy.py
pulumi_gcp_native/apigateway/v1/outputs.py
pulumi_gcp_native/apigateway/v1beta/__init__.py
pulumi_gcp_native/apigateway/v1beta/_inputs.py
pulumi_gcp_native/apigateway/v1beta/api.py
pulumi_gcp_native/apigateway/v1beta/api_config.py
pulumi_gcp_native/apigateway/v1beta/api_config_iam_policy.py
pulumi_gcp_native/apigateway/v1beta/api_iam_policy.py
pulumi_gcp_native/apigateway/v1beta/gateway.py
pulumi_gcp_native/apigateway/v1beta/gateway_iam_policy.py
pulumi_gcp_native/apigateway/v1beta/outputs.py
