Metadata-Version: 2.1
Name: pulumi-gcp-native
Version: 0.0.2a1617829075
Summary: A native Pulumi package for creating and managing Google Cloud resources.
Home-page: https://pulumi.com
License: Apache-2.0
Project-URL: Repository, https://github.com/pulumi/pulumi-gcp-native
Keywords: pulumi google cloud
Platform: UNKNOWN
